dsconfig_wrapper/__init__.py
dsconfig_wrapper/dsconfig_types.py
dsconfig_wrapper/output.py
dsconfig_wrapper-1.1.0.dist-info/METADATA
dsconfig_wrapper-1.1.0.dist-info/WHEEL
dsconfig_wrapper-1.1.0.dist-info/LICENSE
dsconfig_wrapper-1.1.0.dist-info/RECORD
