Metadata-Version: 2.1
Name: dsconfig-wrapper
Version: 1.1.0
Summary: Wraps MAX IV's dsconfig JSON generator to let the user use Python to generate the config
Home-page: https://gitlab.desy.de/cfel-sc-public/dsconfig-wrapper
License: GPL-3.0-or-later
Keywords: Tango
Author: CFEL-SC
Author-email: sc@cfel.de
Requires-Python: >=3.10,<3.12
Classifier: Development Status :: 5 - Production/Stable
Classifier: Environment :: Console
Classifier: Intended Audience :: Developers
Classifier: License :: OSI Approved :: GNU General Public License v3 or later (GPLv3+)
Classifier: Operating System :: OS Independent
Classifier: Programming Language :: Python :: 3
Classifier: Programming Language :: Python :: 3.10
Classifier: Programming Language :: Python :: 3.11
Classifier: Programming Language :: Python :: 3 :: Only
Classifier: Topic :: Database
Classifier: Typing :: Typed
Requires-Dist: dsconfig (==1.6.7)
Requires-Dist: pytango (==9.4.2)
Project-URL: Repository, https://gitlab.desy.de/cfel-sc-public/dsconfig-wrapper
